ublox_gps/__init__.py
ublox_gps/core.py
ublox_gps/sfeSpiWrapper.py
ublox_gps/sparkfun_predefines.py
ublox_gps/test.py
ublox_gps/ublox_gps.py
sparkfun_ublox_gps-1.1.5.dist-info/LICENSE
sparkfun_ublox_gps-1.1.5.dist-info/METADATA
sparkfun_ublox_gps-1.1.5.dist-info/WHEEL
sparkfun_ublox_gps-1.1.5.dist-info/top_level.txt
sparkfun_ublox_gps-1.1.5.dist-info/RECORD
